jobrun/__init__.py
jobrun/commandargs.py
jobrun/config.py
jobrun/i18n.py
jobrun/main.py
jobrun/queue.py
jobrun/readmol.py
jobrun/shared.py
jobrun/submission.py
jobrun/utils.py
jobrun/database/programspecs/autodock.json
jobrun/database/programspecs/demon2k.json
jobrun/database/programspecs/dftbplus.json
jobrun/database/programspecs/gaussian.json
jobrun/database/programspecs/orca.json
jobrun/database/programspecs/vasp.json
jobrun/database/schedulers/lava.json
jobrun/database/schedulers/lsf.json
jobrun/database/schedulers/slurm.json
jobrun/database/schedulers/torque.json
jobrun-0.1.5.data/scripts/jobsync
jobrun-0.1.5.dist-info/LICENSE.md
jobrun-0.1.5.dist-info/METADATA
jobrun-0.1.5.dist-info/WHEEL
jobrun-0.1.5.dist-info/entry_points.txt
jobrun-0.1.5.dist-info/top_level.txt
jobrun-0.1.5.dist-info/RECORD
